{
  "sp1": {
    "123456_s0_p0": "test1",
    "123456_s1_p0": "test2",
    "123456_s2_p0": "test3",
    "123456_s3_p0": "test4",
    "123456_s4_p0": "test5",
    "123456_s5_p0": "test6"
  },
  "sp2": {
    "123456_s0_p1": "test7",
    "123456_s1_p1": "test8",
    "123456_s2_p1": "test9",
    "123456_s3_p1": "test10",
    "123456_s4_p1": "test11",
    "123456_s5_p1": "test12"
  },
  "sp3": {
    "123456_s0_p2": "test13",
    "123456_s1_p2": "test14",
    "123456_s2_p2": "test15",
    "123456_s3_p2": "test16",
    "123456_s4_p2": "test17",
    "123456_s5_p2": "test18"
  },
  "sp4": {
    "123456_s0_p3": "test19",
    "123456_s1_p3": "test20",
    "123456_s2_p3": "test21",
    "123456_s3_p3": "test22",
    "123456_s4_p3": "test23",
    "123456_s5_p3": "test24"
  },
  "sp5": {
    "123456_s0_p4": "test25",
    "123456_s1_p4": "test26",
    "123456_s2_p4": "test27",
    "123456_s3_p4": "test28",
    "123456_s4_p4": "test29",
    "123456_s5_p4": "test30"
  },
  "sp6": {
    "123456_s0_p5": "test31",
    "123456_s1_p5": "test32",
    "123456_s2_p5": "test33",
    "123456_s3_p5": "test34",
    "123456_s4_p5": "test35",
    "123456_s5_p5": "test36"
  }
}
